{
  "buy_items": [
    {"item_id": "health_potion", "price": 30},
    {"item_id": "mid_health_potion", "price": 80},
    {"item_id": "max_health_potion", "price": 200},
    {"item_id": "speed_potion", "price": 50},
    {"item_id": "defense_potion", "price": 60},
    {"item_id": "attack_potion", "price": 80},
    {"item_id": "enhance_stone", "price": 100},
    {"item_id": "mid_enhance_stone", "price": 300},
    {"item_id": "high_enhance_stone", "price": 800},
    {"item_id": "leather_helmet", "price": 40},
    {"item_id": "iron_helmet", "price": 120},
    {"item_id": "bone_amulet", "price": 50},
    {"item_id": "soul_pendant", "price": 150}
  ],
  "sell_prices": {
    "broken_bone": 5,
    "rotten_leather": 5,
    "ghost_fragment": 8,
    "knight_medal": 15,
    "iron_shard": 10,
    "necromancer_dust": 20,
    "soul_crystal": 25,
    "grave_keeper_token": 30,
    "enhance_stone": 50,
    "mid_enhance_stone": 150,
    "high_enhance_stone": 400,
    "boss_enhance_core": 500,
    "iron_boots": 8,
    "knight_greaves": 80,
    "shadow_boots": 200,
    "bone_ring": 6,
    "guardian_ring": 80,
    "overlord_ring": 250,
    "defense_potion": 30,
    "attack_potion": 40,
    "leather_helmet": 12,
    "iron_helmet": 35,
    "knight_helmet": 80,
    "overlord_crown": 250,
    "bone_amulet": 15,
    "soul_pendant": 45,
    "crystal_amulet": 100,
    "shadow_amulet": 250
  }
}
